libspine.dylib
cpyne/.DS_Store
cpyne/__init__.py
cpyne/libspine.dylib
cpyne/spine_bindings.py
cpyne-0.2.0.dist-info/licenses/LICENSE
cpyne-0.2.0.dist-info/.DS_Store
cpyne-0.2.0.dist-info/METADATA
cpyne-0.2.0.dist-info/WHEEL
cpyne-0.2.0.dist-info/top_level.txt
cpyne-0.2.0.dist-info/RECORD
