Metadata-Version: 2.4
Name: cpyne
Version: 0.2.0
Summary: ctypes-based Python binding for Spine Runtime
Author: Daniel
License: MIT License
Requires-Python: >=3.9.7
License-File: LICENSE
Dynamic: license-file
Dynamic: requires-python
